abx_spec_django.py
abx_spec_django-0.1.0.dist-info/METADATA
abx_spec_django-0.1.0.dist-info/WHEEL
abx_spec_django-0.1.0.dist-info/entry_points.txt
abx_spec_django-0.1.0.dist-info/RECORD
